Python/__init__.py
Python/hvs448.pyd
LabSmith_HVS448-2.0.1.dev0.dist-info/LICENSE
LabSmith_HVS448-2.0.1.dev0.dist-info/METADATA
LabSmith_HVS448-2.0.1.dev0.dist-info/WHEEL
LabSmith_HVS448-2.0.1.dev0.dist-info/top_level.txt
LabSmith_HVS448-2.0.1.dev0.dist-info/RECORD
