Metadata-Version: 2.1
Name: LabSmith-HVS448
Version: 2.0.1.dev0
Summary: Python support for controlling the LabSmith HVS448
Home-page: http://www.labsmith.com
Author: LabSmith
Author-email: ecummings@labsmith.com
License: UNKNOWN
Platform: UNKNOWN
Classifier: Programming Language :: Python :: 3.6
Classifier: License :: OSI Approved :: MIT License
Classifier: Operating System :: Microsoft :: Windows
Classifier: Natural Language :: English
